distrem/__init__.py
distrem/distributions.py
distrem/model.py
distrem-0.2.1.dist-info/licenses/LICENSE
distrem-0.2.1.dist-info/METADATA
distrem-0.2.1.dist-info/WHEEL
distrem-0.2.1.dist-info/top_level.txt
distrem-0.2.1.dist-info/RECORD
