Metadata-Version: 2.4
Name: distrem
Version: 0.2.1
Summary: Distribution Ensemble Fitter
Author-email: IHME Math Sciences <ihme.math.sciences@gmail.com>
License: BSD-2-Clause
Project-URL: github, https://github.com/ihmeuw-msca/distrem
Classifier: Programming Language :: Python :: 3
Classifier: License :: OSI Approved :: BSD License
Classifier: Natural Language :: English
Requires-Python: >=3.12
License-File: LICENSE
Requires-Dist: numpy
Requires-Dist: scipy
Requires-Dist: cvxpy
Requires-Dist: matplotlib
Requires-Dist: pandas
Provides-Extra: test
Requires-Dist: pytest; extra == "test"
Requires-Dist: pytest-cov; extra == "test"
Requires-Dist: numpy; extra == "test"
Requires-Dist: scipy; extra == "test"
Requires-Dist: cvxpy; extra == "test"
Provides-Extra: docs
Requires-Dist: sphinx; extra == "docs"
Requires-Dist: sphinx-autodoc-typehints; extra == "docs"
Requires-Dist: furo; extra == "docs"
Dynamic: license-file
